LICENSE
README.md
setup.py
aernetworking/__init__.py
aernetworking/client.py
aernetworking/client_handler.py
aernetworking/server.py
aernetworking/utils.py
aernetworking.egg-info/PKG-INFO
aernetworking.egg-info/SOURCES.txt
aernetworking.egg-info/dependency_links.txt
aernetworking.egg-info/top_level.txt