Metadata-Version: 2.1
Name: aernetworking
Version: 0.0.3
Summary: An easy-to-use network interface module.
Home-page: https://github.com/Aermoss/AerNetworking
Author: Yusuf Rencber
Author-email: yusufrencber546@gmail.com
License: MIT
Keywords: networking
Platform: UNKNOWN
License-File: LICENSE
